rapids_metadata/__init__.py
rapids_metadata/json.py
rapids_metadata/metadata.py
rapids_metadata/py.typed
rapids_metadata/rapids_version.py
rapids_metadata/remote.py
rapids_metadata-0.4.0.dist-info/licenses/LICENSE
rapids_metadata-0.4.0.dist-info/METADATA
rapids_metadata-0.4.0.dist-info/WHEEL
rapids_metadata-0.4.0.dist-info/entry_points.txt
rapids_metadata-0.4.0.dist-info/top_level.txt
rapids_metadata-0.4.0.dist-info/RECORD
