Metadata-Version: 2.4
Name: rapids-metadata
Version: 0.4.0
Summary: metadata for structure of RAPIDS projects
Author-email: RAPIDS Development Team <pypi@rapids.ai>
License: Apache-2.0
Project-URL: Homepage, https://github.com/rapidsai/rapids-metadata
Project-URL: Documentation, https://docs.rapids.ai/
Project-URL: Source, https://github.com/rapidsai/rapids-metadata
Classifier: License :: OSI Approved :: Apache Software License
Classifier: Programming Language :: Python :: 3
Requires-Python: >=3.9
License-File: LICENSE
Requires-Dist: packaging
Requires-Dist: pydantic
Provides-Extra: test
Requires-Dist: pytest; extra == "test"
Requires-Dist: pytest-httpserver; extra == "test"
Dynamic: license-file
